gfeat/UTR.py
gfeat/__init__.py
gfeat/expression_design_matrix.py
gfeat/gene.py
gfeat/genome.py
gfeat/gfeat.py
gfeat/score_UTRs.py
gfeat/transcript.py
gfeat/units.py
gfeat/upstreamAUG.py
gfeat/utils.py
gfeat-1.0.0.dist-info/METADATA
gfeat-1.0.0.dist-info/RECORD
gfeat-1.0.0.dist-info/WHEEL
gfeat-1.0.0.dist-info/top_level.txt
tests/.DS_Store
tests/__init__.py
tests/test_gfeat.py
tests/UTR/config_UTR.py
tests/UTR/test_FivePrimeUTRSeq_constructor.py
tests/UTR/test_FivePrimeUTRSeq_getitem.py
tests/UTR/test_FivePrimeUTRSeq_len.py
tests/data/49470G_chr22_testing.vcf
tests/data/49470G_chr22_testing.vcf.gz
tests/data/49470G_chr22_testing.vcf.gz.tbi
tests/data/check_pyensemble.gtf
tests/data/check_scoreUTRs.fa
tests/data/check_scoreUTRs.gtf
tests/data/chr22_testing.fa
tests/data/chr22_testing.fa.fai
tests/data/chr22_testing.gtf
tests/data/gencode.v24.annotation_chr22.gtf
tests/data/gencode.v24.annotation_chr22_FivePrimeUTRSeq_testing.gtf
tests/data/gencode.v24.annotation_chr22_FivePrimeUTRSeq_testing_minus-strand.gtf
tests/data/hg38_chr22.fa
tests/data/hg38_chr22.fa.fai
tests/gene/config_1.py
tests/gene/test_coding_sequence_codon_count.py
tests/transcript/config.py
tests/transcript/test_GC_content.py
tests/transcript/test_Kozak.py
tests/transcript/test_codon_counts.py
tests/transcript/test_codon_usage.py
tests/transcript/test_get_codon_pairs_frequency.py
tests/transcript/test_stop_codon_context.py
tests/transcript/test_utr3_motif_counts.py
tests/transcript/test_utr5_motif_counts.py
tests/uATG/config_uATG.py
tests/uATG/test_predict_on_batch.py
tests/uATG/test_predict_on_sample.py
tests/uATG/test_predict_on_sample_with_pos.py
tests/units/test_extract_sequence_BedTool.py
tests/units/test_mutate_sequence_BedTool.py
tests/utils/test_PCA_with_scaling.py
