Metadata-Version: 2.1
Name: gfeat
Version: 1.0.0
Summary: Python genomic features extractor from raw files.
Home-page: https://github.com/gagneurlab/gfeat
Author: Veronika Kotova
Author-email: kotova@in.tum.de
License: MIT license
Keywords: gfeat
Platform: UNKNOWN
Classifier: Programming Language :: Python :: 3.5
Provides-Extra: develop
Requires-Dist: pyensembl (==1.1.0)
Requires-Dist: gtfparse (==0.0.6)
Requires-Dist: datacache (==0.4.20)
Requires-Dist: simplejson (==3.12.0)
Requires-Dist: typechecks (==0.0.2)
Requires-Dist: pytest
Requires-Dist: pysam
Requires-Dist: pybedtools
Requires-Dist: cyvcf2
Requires-Dist: numpy
Requires-Dist: scikit-learn
Requires-Dist: pandas
Provides-Extra: develop
Requires-Dist: bumpversion; extra == 'develop'
Requires-Dist: wheel; extra == 'develop'
Requires-Dist: jedi; extra == 'develop'
Requires-Dist: epc; extra == 'develop'
Requires-Dist: pytest; extra == 'develop'
Requires-Dist: pytest-pep8; extra == 'develop'
Requires-Dist: pytest-cov; extra == 'develop'
